_cppinyin.cp312-win_amd64.pyd
cppinyin_core.lib
cppinyin/__init__.py
cppinyin/cli.py
cppinyin/cppinyin.py
cppinyin/resources/pinyin.dict
cppinyin/resources/pinyin.raw
cppinyin-0.11.dist-info/licenses/LICENSE
cppinyin-0.11.dist-info/METADATA
cppinyin-0.11.dist-info/WHEEL
cppinyin-0.11.dist-info/entry_points.txt
cppinyin-0.11.dist-info/top_level.txt
cppinyin-0.11.dist-info/RECORD
