Metadata-Version: 2.4
Name: cppinyin
Version: 0.11
Summary: A simple and fast pinyin encoder and decoder.
Author-email: Next-gen Kaldi development team <wkang@pku.edu.cn>
Project-URL: Homepage, https://github.com/pkufool/cppinyin
Project-URL: Bug Tracker, https://github.com/pkufool/cppinyin/issues
Classifier: Programming Language :: Python :: 3
Classifier: License :: OSI Approved :: Apache Software License
Classifier: Operating System :: OS Independent
Requires-Python: >=3.7
License-File: LICENSE
Requires-Dist: importlib-resources
Requires-Dist: click
Dynamic: license-file
